glpg/__init__.py
glpg/definitions.py
glpg/camera/__init__.py
glpg/camera/camera.py
glpg/camera/fly_motion.py
glpg/display/__init__.py
glpg/display/base.py
glpg/display/gl_screen.py
glpg/display/gl_widget.py
glpg/input/__init__.py
glpg/input/keyboard.py
glpg/input/menu.py
glpg/input/mouse.py
glpg/rendering/__init__.py
glpg/rendering/methods.py
glpg/rendering/textures.py
glpg/rendering/gpu/__init__.py
glpg/rendering/gpu/shader.py
glpg/rendering/gpu/vao.py
glpg/rendering/lighting/__init__.py
glpg/rendering/lighting/light.py
glpg/rendering/lighting/lights.py
glpg/rendering/models/__init__.py
glpg/rendering/models/model.py
glpg/rendering/models/point_cloud.py
glpg/rendering/models/model_generation/__init__.py
glpg/rendering/models/model_generation/geometry.py
glpg/shader/__init__.py
glpg/shader/base/__init__.py
glpg/shader/base/blinn_phong/__init__.py
glpg/shader/base/blinn_phong/blinn_phong.py
glpg/shader/base/flat/__init__.py
glpg/shader/base/flat/flat.py
glpg/shader/base/gouraud/__init__.py
glpg/shader/base/gouraud/gouraud.py
glpg/shader/base/toon/__init__.py
glpg/shader/base/toon/toon.py
glpg/texturing/__init__.py
glpg/texturing/methods.py
glpg/texturing/texture.py
glpg/transformations/__init__.py
glpg/transformations/methods.py
glpg-1.0.0.dist-info/LICENSE.rst
glpg-1.0.0.dist-info/METADATA
glpg-1.0.0.dist-info/WHEEL
glpg-1.0.0.dist-info/top_level.txt
glpg-1.0.0.dist-info/RECORD
